cryoet_data_portal/__init__.py
cryoet_data_portal/_client.py
cryoet_data_portal/_codegen.py
cryoet_data_portal/_constants.py
cryoet_data_portal/_file_tools.py
cryoet_data_portal/_gql_base.py
cryoet_data_portal/_models.py
cryoet_data_portal/_version.py
cryoet_data_portal/data/schema.graphql
cryoet_data_portal/templates/Annotation.jinja2
cryoet_data_portal/templates/AnnotationFile.jinja2
cryoet_data_portal/templates/Dataset.jinja2
cryoet_data_portal/templates/Footer.jinja2
cryoet_data_portal/templates/Header.jinja2
cryoet_data_portal/templates/Model.jinja2
cryoet_data_portal/templates/Run.jinja2
cryoet_data_portal/templates/TiltSeries.jinja2
cryoet_data_portal/templates/Tomogram.jinja2
cryoet_data_portal/templates/TomogramVoxelSpacing.jinja2
cryoet_data_portal-4.5.0.dist-info/licenses/LICENSE
cryoet_data_portal-4.5.0.dist-info/METADATA
cryoet_data_portal-4.5.0.dist-info/WHEEL
cryoet_data_portal-4.5.0.dist-info/top_level.txt
cryoet_data_portal-4.5.0.dist-info/RECORD
