Metadata-Version: 2.4
Name: cryoet_data_portal
Version: 4.5.0
Summary: API Client to facilitate the use of the CryoET Portal. For more information about the API and the project visit https://github.com/chanzuckerberg/cryoet-data-portal/
Author-email: Chan Zuckerberg Initiative <cryoetdataportal@chanzuckerberg.com>
License: MIT
Project-URL: homepage, https://github.com/chanzuckerberg/cryoet-data-portal
Project-URL: repository, https://github.com/chanzuckerberg/cryoet-data-portal
Project-URL: documentation, https://chanzuckerberg.github.io/cryoet-data-portal/python-api.html
Classifier: Development Status :: 4 - Beta
Classifier: Intended Audience :: Developers
Classifier: Intended Audience :: Information Technology
Classifier: Intended Audience :: Science/Research
Classifier: License :: OSI Approved :: MIT License
Classifier: Programming Language :: Python
Classifier: Topic :: Scientific/Engineering :: Bio-Informatics
Classifier: Operating System :: POSIX :: Linux
Classifier: Operating System :: MacOS :: MacOS X
Classifier: Programming Language :: Python :: 3.7
Classifier: Programming Language :: Python :: 3.8
Classifier: Programming Language :: Python :: 3.9
Classifier: Programming Language :: Python :: 3.10
Requires-Python: >=3.7
License-File: LICENSE
Requires-Dist: requests<3.0,>=2.0
Requires-Dist: boto3<2.0,>=1.0.0
Requires-Dist: deepmerge<3.0,>=2.0
Requires-Dist: gql[requests]<4.0,>=3.0
Requires-Dist: tqdm<5.0,>=4.67
Requires-Dist: strcase<2.0,>=1.0.0
Requires-Dist: jinja2<4.0,>=3.0
Dynamic: license-file
